__init__.py
morefractions.py
morefractions-0.1.0.dist-info/LICENSE
morefractions-0.1.0.dist-info/METADATA
morefractions-0.1.0.dist-info/WHEEL
morefractions-0.1.0.dist-info/top_level.txt
morefractions-0.1.0.dist-info/RECORD
