Metadata-Version: 2.1
Name: morefractions
Version: 0.1.0
Summary: A package with classes and functions for manipulating fractions
Author-email: Te Du <tdu0915@gmail.com>
Maintainer-email: Te Du <tdu0915@gmail.com>
License: Te's License
Project-URL: Homepage, https://github.com/meowdog011011/morefractions-py
Project-URL: Repository, https://github.com/meowdog011011/morefractions-py.git
Project-URL: Issues, https://github.com/meowdog011011/morefractions-py/issues
Project-URL: Changelog, https://github.com/meowdog011011/morefractions-py/CHANGELOG.md
Keywords: fraction,fractions
Classifier: Development Status :: 4 - Beta
Classifier: Programming Language :: Python :: 3
Classifier: Programming Language :: Python :: 3.10
Classifier: Programming Language :: Python :: 3.11
Classifier: Programming Language :: Python :: 3.12
Classifier: Operating System :: OS Independent
Requires-Python: >=3.10
License-File: LICENSE
